spryx_message/__init__.py
spryx_message/client.py
spryx_message/resources/__init__.py
spryx_message/resources/channels.py
spryx_message/resources/contacts.py
spryx_message/resources/files.py
spryx_message/resources/messages.py
spryx_message/swagger.json
spryx_message/types/__init__.py
spryx_message/types/channel.py
spryx_message/types/message.py
spryx_message-0.1.5.dist-info/LICENSE
spryx_message-0.1.5.dist-info/METADATA
spryx_message-0.1.5.dist-info/WHEEL
spryx_message-0.1.5.dist-info/RECORD
