Metadata-Version: 2.3
Name: spryx-message
Version: 0.1.5
Summary: 
Author: Luiz Henrique
Author-email: luiz@spryx.ai
Requires-Python: >=3.11
Classifier: Programming Language :: Python :: 3
Classifier: Programming Language :: Python :: 3.11
Classifier: Programming Language :: Python :: 3.12
Classifier: Programming Language :: Python :: 3.13
Requires-Dist: spryx-http (>=0.2.7)
